yixinPyLib/__init__.py
yixinPyLib/Library/AndroidMethod.py
yixinPyLib/Library/AppMethod.py
yixinPyLib/Library/IosMethod.py
yixinPyLib/Library/Logger.py
yixinPyLib/Library/ScriptMethod.py
yixinPyLib/Library/SeleniumMethod.py
yixinPyLib/Library/__init__.py
yixinPyLib/LocalMethod/UserClass.py
yixinPyLib/LocalMethod/__init__.py
yixinPyLib/demo/__init__.py
yixinPyLib/demo/hello.py
yixinPyLib/testcaseupload/__init__.py
yixinPyLib/testcaseupload/runTest.py
yixinPyLib/testcaseupload/uploadFile.py
yixinPyLib/testcaseupload/uploadTestcase.py
yixinPyLib-0.0.57.dist-info/DESCRIPTION.rst
yixinPyLib-0.0.57.dist-info/METADATA
yixinPyLib-0.0.57.dist-info/RECORD
yixinPyLib-0.0.57.dist-info/WHEEL
yixinPyLib-0.0.57.dist-info/metadata.json
yixinPyLib-0.0.57.dist-info/top_level.txt
