Metadata-Version: 2.0
Name: yixinPyLib
Version: 0.0.57
Summary: 易鑫金融测试用例公共库
Home-page: http://192.168.145.20:8088/testsite
Author: Zhouxs
Author-email: zhouxs@yixincapital.com
License: MIT
Keywords: public library test case python
Platform: UNKNOWN
Classifier: Development Status :: 4 - Beta
Classifier: Intended Audience :: Developers
Classifier: Topic :: Software Development :: Build Tools
Classifier: License :: OSI Approved :: MIT License
Classifier: Programming Language :: Python :: 2.6
Classifier: Programming Language :: Python :: 2.7
